voraus_opcua_generator/__init__.py
voraus_opcua_generator/formatter.py
voraus_opcua_generator/generator.py
voraus_opcua_generator/py.typed
voraus_opcua_generator/rc_export.py
voraus_opcua_generator/schema.py
voraus_opcua_generator/templates.py
voraus_opcua_generator/cli/__init__.py
voraus_opcua_generator/cli/cli.py
voraus_opcua_generator/cli/data_legacy_builder.py
voraus_opcua_generator/cli/doc_builder.py
voraus_opcua_generator/cli/py_client_builder.py
voraus_opcua_generator/cli/xml_builder.py
voraus_opcua_generator/client_generator_python/__init__.py
voraus_opcua_generator/client_generator_python/package_base.py
voraus_opcua_generator/client_generator_python/utils.py
voraus_opcua_generator/data_generator_legacy/__init__.py
voraus_opcua_generator/data_generator_legacy/generator.py
voraus_opcua_generator/doc_builder/__init__.py
voraus_opcua_generator/doc_builder/argument.py
voraus_opcua_generator/doc_builder/method.py
voraus_opcua_generator/doc_builder/node.py
voraus_opcua_generator/doc_builder/obj.py
voraus_opcua_generator/doc_builder/overview.py
voraus_opcua_generator/doc_builder/parser.py
voraus_opcua_generator/doc_builder/rst.py
voraus_opcua_generator/doc_builder/types.py
voraus_opcua_generator/doc_builder/utils.py
voraus_opcua_generator/doc_builder/variable.py
voraus_opcua_generator/parser/__init__.py
voraus_opcua_generator/parser/client_parser.py
voraus_opcua_generator/parser/nodeset_parser.py
voraus_opcua_generator/source_builder/__init__.py
voraus_opcua_generator/source_builder/indent_manager.py
voraus_opcua_generator/source_builder/source_builder.py
voraus_opcua_generator/templates/client_python/__init__.py.j2
voraus_opcua_generator/templates/client_python/_overview.py.j2
voraus_opcua_generator/templates/client_python/_util.py.j2
voraus_opcua_generator/templates/client_python/module.py.j2
voraus_opcua_generator/templates/client_python/overview.__init__.py.j2
voraus_opcua_generator/templates/client_python/util.__init__.py.j2
voraus_opcua_generator-0.14.0.dist-info/LICENSE.txt
voraus_opcua_generator-0.14.0.dist-info/METADATA
voraus_opcua_generator-0.14.0.dist-info/WHEEL
voraus_opcua_generator-0.14.0.dist-info/entry_points.txt
voraus_opcua_generator-0.14.0.dist-info/top_level.txt
voraus_opcua_generator-0.14.0.dist-info/RECORD
