Metadata-Version: 2.1
Name: voraus-opcua-generator
Version: 0.14.0
Summary: A library for robots that helps with a lot of things.
Home-page: https://github.com/vorausrobotik/voraus-opcua-generator
Author: Jan-Niklas Burfeind
Author-email: jan-niklas.burfeind@vorausrobotik.com
License: commercial
Requires-Python: >=3.11
License-File: LICENSE.txt
Requires-Dist: importlib-metadata
Requires-Dist: voraus-logging-lib
Requires-Dist: asyncua
Requires-Dist: Jinja2
Requires-Dist: typer
Provides-Extra: dev
Requires-Dist: tox==4.15.1; extra == "dev"
Requires-Dist: isort==5.13.2; extra == "dev"
Requires-Dist: black==24.4.2; extra == "dev"
Requires-Dist: mypy==1.10.1; extra == "dev"
Requires-Dist: pylint==3.2.5; extra == "dev"
Requires-Dist: pytest==8.2.2; extra == "dev"
Requires-Dist: types-docutils; extra == "dev"
Requires-Dist: types-setuptools; extra == "dev"
Requires-Dist: jinja2==3.1.4; extra == "dev"
Requires-Dist: ruff==0.5.0; extra == "dev"
Requires-Dist: black; extra == "dev"
Requires-Dist: isort; extra == "dev"
Requires-Dist: voraus-opc-ua-spec-robot-control~=6.1.1; extra == "dev"
Requires-Dist: pytest==8.2.2; extra == "dev"
Requires-Dist: pytest-randomly==3.15.0; extra == "dev"
Requires-Dist: pytest-cov==5.0.0; extra == "dev"
Requires-Dist: coverage[toml]==7.5.4; extra == "dev"
Requires-Dist: black; extra == "dev"
Requires-Dist: isort; extra == "dev"
Requires-Dist: pytest-mock; extra == "dev"
Requires-Dist: voraus-opc-ua-spec-robot-control~=6.1.1; extra == "dev"
Requires-Dist: sphinx==7.3.7; extra == "dev"
Requires-Dist: sphinxawesome-theme==5.2.0; extra == "dev"
Requires-Dist: sphinx-selective-exclude==1.0.3; extra == "dev"
Requires-Dist: sphinx-autodoc-typehints==2.2.2; extra == "dev"
Requires-Dist: pip-licenses==4.4.0; extra == "dev"
Requires-Dist: jinja2==3.1.4; extra == "dev"
Requires-Dist: build[virtualenv]==1.2.1; extra == "dev"
Provides-Extra: lint
Requires-Dist: isort==5.13.2; extra == "lint"
Requires-Dist: black==24.4.2; extra == "lint"
Requires-Dist: mypy==1.10.1; extra == "lint"
Requires-Dist: pylint==3.2.5; extra == "lint"
Requires-Dist: pytest==8.2.2; extra == "lint"
Requires-Dist: types-docutils; extra == "lint"
Requires-Dist: types-setuptools; extra == "lint"
Requires-Dist: jinja2==3.1.4; extra == "lint"
Requires-Dist: ruff==0.5.0; extra == "lint"
Requires-Dist: black; extra == "lint"
Requires-Dist: isort; extra == "lint"
Requires-Dist: voraus-opc-ua-spec-robot-control~=6.1.1; extra == "lint"
Provides-Extra: test
Requires-Dist: pytest==8.2.2; extra == "test"
Requires-Dist: pytest-randomly==3.15.0; extra == "test"
Requires-Dist: pytest-cov==5.0.0; extra == "test"
Requires-Dist: coverage[toml]==7.5.4; extra == "test"
Requires-Dist: black; extra == "test"
Requires-Dist: isort; extra == "test"
Requires-Dist: pytest-mock; extra == "test"
Requires-Dist: voraus-opc-ua-spec-robot-control~=6.1.1; extra == "test"
Provides-Extra: doc
Requires-Dist: sphinx==7.3.7; extra == "doc"
Requires-Dist: sphinxawesome-theme==5.2.0; extra == "doc"
Requires-Dist: sphinx-selective-exclude==1.0.3; extra == "doc"
Requires-Dist: sphinx-autodoc-typehints==2.2.2; extra == "doc"
Requires-Dist: pip-licenses==4.4.0; extra == "doc"
Requires-Dist: jinja2==3.1.4; extra == "doc"
Provides-Extra: build
Requires-Dist: build[virtualenv]==1.2.1; extra == "build"
Provides-Extra: tox
Requires-Dist: tox==4.15.1; extra == "tox"
Provides-Extra: lint-template
Requires-Dist: isort==5.13.2; extra == "lint-template"
Requires-Dist: black==24.4.2; extra == "lint-template"
Requires-Dist: mypy==1.10.1; extra == "lint-template"
Requires-Dist: pylint==3.2.5; extra == "lint-template"
Requires-Dist: pytest==8.2.2; extra == "lint-template"
Requires-Dist: types-docutils; extra == "lint-template"
Requires-Dist: types-setuptools; extra == "lint-template"
Requires-Dist: jinja2==3.1.4; extra == "lint-template"
Requires-Dist: ruff==0.5.0; extra == "lint-template"
Provides-Extra: test-template
Requires-Dist: pytest==8.2.2; extra == "test-template"
Requires-Dist: pytest-randomly==3.15.0; extra == "test-template"
Requires-Dist: pytest-cov==5.0.0; extra == "test-template"
Requires-Dist: coverage[toml]==7.5.4; extra == "test-template"
Provides-Extra: doc-template
Requires-Dist: sphinx==7.3.7; extra == "doc-template"
Requires-Dist: sphinxawesome-theme==5.2.0; extra == "doc-template"
Requires-Dist: sphinx-selective-exclude==1.0.3; extra == "doc-template"
Requires-Dist: sphinx-autodoc-typehints==2.2.2; extra == "doc-template"
Requires-Dist: pip-licenses==4.4.0; extra == "doc-template"
Requires-Dist: jinja2==3.1.4; extra == "doc-template"
Provides-Extra: build-template
Requires-Dist: build[virtualenv]==1.2.1; extra == "build-template"
